setup.py
sqlitecookiejar.py
sqlitecookiejar.egg-info/PKG-INFO
sqlitecookiejar.egg-info/SOURCES.txt
sqlitecookiejar.egg-info/dependency_links.txt
sqlitecookiejar.egg-info/not-zip-safe
sqlitecookiejar.egg-info/top_level.txt