Metadata-Version: 1.1
Name: sqlitecookiejar
Version: 1.0.1
Summary: FileCookieJar using SQLite files for persistence
Home-page: https://github.com/timsoft-oss/sqlitecookiejar
Author: UNKNOWN
Author-email: dgarnier@timsoft.com
License: Apache 2.0
Platform: UNKNOWN
Classifier: Development Status :: 5 - Production/Stable
Classifier: Environment :: Web Environment
Classifier: Intended Audience :: Developers
Classifier: License :: OSI Approved :: Apache Software License
Classifier: Programming Language :: Python
Classifier: Programming Language :: Python :: 2.7
Classifier: Topic :: Internet :: WWW/HTTP :: Session
